{
  "updated_at": "2026-04-29T15:03:00.789152+00:00",
  "market_status": "open",
  "pfgc": {
    "price": 88.04,
    "change": 0.14,
    "change_pct": 0.16,
    "market_cap": 13830993407.0,
    "pe": 39.84,
    "eps": 2.21,
    "volume": 149921,
    "avg_volume": 2188859,
    "day_low": 86.5,
    "day_high": 88.39,
    "year_low": 77.44,
    "year_high": 109.05,
    "prev_close": 87.9,
    "open": 87.29,
    "market_status": "open",
    "base_target": 72.5,
    "base_return_pct": -17.7,
    "bear_target": 57.6,
    "bear_return_pct": -34.6,
    "bull_target": 98.0,
    "bull_return_pct": 11.3
  },
  "usfd": {
    "price": 91.28,
    "change": 0.9,
    "change_pct": 1.0,
    "market_cap": 20131067466.0,
    "pe": 31.05,
    "eps": 2.94,
    "volume": 135886,
    "avg_volume": 2691395,
    "day_low": 90.28,
    "day_high": 91.58,
    "year_low": 64.08,
    "year_high": 102.13,
    "prev_close": 90.38,
    "open": 91.35,
    "market_status": "open"
  },
  "syy": {
    "price": 73.64,
    "change": 0.27,
    "change_pct": 0.37,
    "market_cap": 35268454023.0,
    "pe": 20.46,
    "eps": 3.6,
    "volume": 1464526,
    "avg_volume": 4853565,
    "day_low": 72.5,
    "day_high": 73.7,
    "year_low": 68.19,
    "year_high": 91.85,
    "prev_close": 73.37,
    "open": 72.5,
    "market_status": "open"
  },
  "peer_pe_spread": {
    "pfgc_pe": 39.84,
    "usfd_pe": 31.05,
    "syy_pe": 20.46,
    "pfgc_premium_to_usfd_pct": 28.3,
    "pfgc_premium_to_syy_pct": 94.7
  }
}