{
  "updated_at": "2026-04-07T20:10:06.118136+00:00",
  "market_status": "after_hours",
  "pfgc": {
    "price": 84.15,
    "change": -1.82,
    "change_pct": -2.12,
    "market_cap": 13219878410.0,
    "pe": 38.08,
    "eps": 2.21,
    "volume": 1426547,
    "avg_volume": 2311791,
    "day_low": 83.5,
    "day_high": 86.0,
    "year_low": 70.42,
    "year_high": 109.05,
    "prev_close": 85.97,
    "open": 85.63,
    "market_status": "after_hours",
    "base_target": 72.5,
    "base_return_pct": -13.8,
    "bear_target": 57.6,
    "bear_return_pct": -31.6,
    "bull_target": 98.0,
    "bull_return_pct": 16.5
  },
  "usfd": {
    "price": 89.36,
    "change": -1.54,
    "change_pct": -1.7,
    "market_cap": 19923159641.0,
    "pe": 30.4,
    "eps": 2.94,
    "volume": 980487,
    "avg_volume": 2879260,
    "day_low": 88.96,
    "day_high": 91.39,
    "year_low": 59.43,
    "year_high": 102.13,
    "prev_close": 90.91,
    "open": 90.55,
    "market_status": "after_hours"
  },
  "syy": {
    "price": 73.26,
    "change": 0.02,
    "change_pct": 0.03,
    "market_cap": 35086459492.0,
    "pe": 19.75,
    "eps": 3.71,
    "volume": 3842216,
    "avg_volume": 4570238,
    "day_low": 71.99,
    "day_high": 73.88,
    "year_low": 67.12,
    "year_high": 91.85,
    "prev_close": 73.24,
    "open": 72.57,
    "market_status": "after_hours"
  },
  "peer_pe_spread": {
    "pfgc_pe": 38.08,
    "usfd_pe": 30.4,
    "syy_pe": 19.75,
    "pfgc_premium_to_usfd_pct": 25.3,
    "pfgc_premium_to_syy_pct": 92.8
  }
}